whichnet/__init__.py
whichnet/whichnet.py
whichnet-0.1.2.dist-info/METADATA
whichnet-0.1.2.dist-info/WHEEL
whichnet-0.1.2.dist-info/entry_points.txt
whichnet-0.1.2.dist-info/licenses/LICENSE
whichnet-0.1.2.dist-info/RECORD
